airflow/__init__.py
airflow/alembic.ini
airflow/configuration.py
airflow/default_login.py
airflow/exceptions.py
airflow/jobs.py
airflow/logging_config.py
airflow/minihivecluster.py
airflow/models.py
airflow/plugins_manager.py
airflow/settings.py
airflow/version.py
airflow/api/__init__.py
airflow/api/auth/__init__.py
airflow/api/auth/backend/__init__.py
airflow/api/auth/backend/default.py
airflow/api/auth/backend/deny_all.py
airflow/api/auth/backend/kerberos_auth.py
airflow/api/client/__init__.py
airflow/api/client/api_client.py
airflow/api/client/json_client.py
airflow/api/client/local_client.py
airflow/api/common/__init__.py
airflow/api/common/experimental/__init__.py
airflow/api/common/experimental/delete_dag.py
airflow/api/common/experimental/get_dag_run_state.py
airflow/api/common/experimental/get_dag_runs.py
airflow/api/common/experimental/get_task.py
airflow/api/common/experimental/get_task_instance.py
airflow/api/common/experimental/mark_tasks.py
airflow/api/common/experimental/pool.py
airflow/api/common/experimental/trigger_dag.py
airflow/bin/__init__.py
airflow/bin/airflow
airflow/bin/cli.py
airflow/config_templates/__init__.py
airflow/config_templates/airflow_local_settings.py
airflow/config_templates/default_airflow.cfg
airflow/config_templates/default_celery.py
airflow/config_templates/default_test.cfg
airflow/config_templates/default_webserver_config.py
airflow/contrib/__init__.py
airflow/contrib/auth/__init__.py
airflow/contrib/auth/backends/__init__.py
airflow/contrib/auth/backends/github_enterprise_auth.py
airflow/contrib/auth/backends/google_auth.py
airflow/contrib/auth/backends/kerberos_auth.py
airflow/contrib/auth/backends/ldap_auth.py
airflow/contrib/auth/backends/password_auth.py
airflow/contrib/executors/__init__.py
airflow/contrib/executors/kubernetes_executor.py
airflow/contrib/executors/mesos_executor.py
airflow/contrib/hooks/__init__.py
airflow/contrib/hooks/aws_dynamodb_hook.py
alo7_airflow-1.10.0.7.dist-info/METADATA
alo7_airflow-1.10.0.7.dist-info/RECORD
alo7_airflow-1.10.0.7.dist-info/WHEEL
alo7_airflow-1.10.0.7.dist-info/top_level.txt
