Metadata-Version: 2.1
Name: alo7-airflow
Version: 1.10.0.7
Summary: Programmatically author, schedule and monitor data pipelines
Home-page: http://airflow.incubator.apache.org/
Author: Apache Software Foundation
Author-email: dev@airflow.incubator.apache.org
License: Apache License 2.0
Download-URL: https://dist.apache.org/repos/dist/release/incubator/airflow/1.10.0.7
Platform: UNKNOWN
Classifier: Development Status :: 5 - Production/Stable
Classifier: Environment :: Console
Classifier: Environment :: Web Environment
Classifier: Intended Audience :: Developers
Classifier: Intended Audience :: System Administrators
Classifier: License :: OSI Approved :: Apache Software License
Classifier: Programming Language :: Python :: 2.7
Classifier: Programming Language :: Python :: 3.4
Classifier: Topic :: System :: Monitoring
Provides-Extra: databricks
Provides-Extra: devel_hadoop
Provides-Extra: winrm
Provides-Extra: jira
Provides-Extra: devel
Provides-Extra: druid
Provides-Extra: sendgrid
Provides-Extra: all_dbs
Provides-Extra: azure_data_lake
Provides-Extra: snowflake
Provides-Extra: vertica
Provides-Extra: pinot
Provides-Extra: docker
Provides-Extra: oracle
Provides-Extra: async
Provides-Extra: cloudant
Provides-Extra: atlas
Provides-Extra: datadog
Provides-Extra: mongo
Provides-Extra: ldap
Provides-Extra: mysql
Provides-Extra: ssh
Provides-Extra: all
Provides-Extra: password
Provides-Extra: statsd
Provides-Extra: github_enterprise
Provides-Extra: gcp_api
Provides-Extra: kerberos
Provides-Extra: s3
Provides-Extra: webhdfs
Provides-Extra: samba
Provides-Extra: segment
Provides-Extra: devel_ci
Provides-Extra: salesforce
Provides-Extra: cassandra
Provides-Extra: elasticsearch
Provides-Extra: celery
Provides-Extra: emr
Provides-Extra: hive
Provides-Extra: doc
Provides-Extra: redis
Provides-Extra: azure_blob_storage
Provides-Extra: crypto
Provides-Extra: rabbitmq
Provides-Extra: qds
Provides-Extra: mssql
Provides-Extra: jdbc
Provides-Extra: dask
Provides-Extra: slack
Provides-Extra: kubernetes
Provides-Extra: postgres
Provides-Extra: cgroups
Provides-Extra: hdfs
Requires-Dist: alembic (<0.9,>=0.8.3)
Requires-Dist: bleach (==2.1.2)
Requires-Dist: configparser (<3.6.0,>=3.5.0)
Requires-Dist: croniter (<0.4,>=0.3.17)
Requires-Dist: dill (<0.3,>=0.2.2)
Requires-Dist: flask (<0.13,>=0.12.4)
Requires-Dist: flask-appbuilder (<2.0.0,>=1.11.1)
Requires-Dist: flask-admin (==1.4.1)
Requires-Dist: flask-caching (<1.4.0,>=1.3.3)
Requires-Dist: flask-login (==0.2.11)
Requires-Dist: flask-swagger (==0.2.13)
Requires-Dist: flask-wtf (<0.15,>=0.14.2)
Requires-Dist: funcsigs (==1.0.0)
Requires-Dist: future (<0.17,>=0.16.0)
Requires-Dist: gitpython (>=2.0.2)
Requires-Dist: gunicorn (<20.0,>=19.4.0)
Requires-Dist: iso8601 (>=0.1.12)
Requires-Dist: jinja2 (<2.9.0,>=2.7.3)
Requires-Dist: lxml (<4.0,>=3.6.0)
Requires-Dist: markdown (<3.0,>=2.5.2)
Requires-Dist: pandas (<1.0.0,>=0.17.1)
Requires-Dist: pendulum (==1.4.4)
Requires-Dist: psutil (<5.0.0,>=4.2.0)
Requires-Dist: pygments (<3.0,>=2.0.1)
Requires-Dist: python-daemon (<2.2,>=2.1.1)
Requires-Dist: python-dateutil (<3,>=2.3)
Requires-Dist: python-nvd3 (==0.15.0)
Requires-Dist: requests (<3,>=2.5.1)
Requires-Dist: setproctitle (<2,>=1.1.8)
Requires-Dist: sqlalchemy (<1.2.0,>=1.1.15)
Requires-Dist: sqlalchemy-utc (>=0.9.0)
Requires-Dist: tabulate (<0.8.0,>=0.7.5)
Requires-Dist: tenacity (==4.8.0)
Requires-Dist: thrift (>=0.9.2)
Requires-Dist: tzlocal (>=1.4)
Requires-Dist: unicodecsv (>=0.14.1)
Requires-Dist: werkzeug (<0.15.0,>=0.14.1)
Requires-Dist: zope.deprecation (<5.0,>=4.0)
Provides-Extra: all
Requires-Dist: sendgrid (>=5.2.0); extra == 'all'
Requires-Dist: click; extra == 'all'
Requires-Dist: freezegun; extra == 'all'
Requires-Dist: jira; extra == 'all'
Requires-Dist: lxml (>=3.3.4); extra == 'all'
Requires-Dist: mock; extra == 'all'
Requires-Dist: mongomock; extra == 'all'
Requires-Dist: moto (==1.1.19); extra == 'all'
Requires-Dist: nose; extra == 'all'
Requires-Dist: nose-ignore-docstring (==0.2); extra == 'all'
Requires-Dist: nose-timer; extra == 'all'
Requires-Dist: parameterized; extra == 'all'
Requires-Dist: paramiko; extra == 'all'
Requires-Dist: pysftp; extra == 'all'
Requires-Dist: pywinrm; extra == 'all'
Requires-Dist: qds-sdk (>=1.9.6); extra == 'all'
Requires-Dist: rednose; extra == 'all'
Requires-Dist: requests-mock; extra == 'all'
Requires-Dist: psycopg2-binary (>=2.7.4); extra == 'all'
Requires-Dist: mysqlclient (>=1.3.6); extra == 'all'
Requires-Dist: hmsclient (>=0.1.0); extra == 'all'
Requires-Dist: pyhive (>=0.6.0); extra == 'all'
Requires-Dist: pymssql (>=2.1.1); extra == 'all'
Requires-Dist: snakebite (>=2.7.8); extra == 'all'
Requires-Dist: vertica-python (>=0.5.1); extra == 'all'
Requires-Dist: cloudant (<2.0,>=0.5.9); extra == 'all'
Requires-Dist: pydruid (>=0.4.1); extra == 'all'
Requires-Dist: pinotdb (>=0.1.1); extra == 'all'
Requires-Dist: cassandra-driver (>=3.13.0); extra == 'all'
Requires-Dist: pymongo (>=3.6.0); extra == 'all'
Requires-Dist: sphinx (>=1.2.3); extra == 'all'
Requires-Dist: sphinx-argparse (>=0.1.13); extra == 'all'
Requires-Dist: sphinx-rtd-theme (>=0.1.6); extra == 'all'
Requires-Dist: Sphinx-PyPI-upload (>=0.2.1); extra == 'all'
Requires-Dist: pysmbclient (>=0.1.3); extra == 'all'
Requires-Dist: boto3 (>=1.7.0); extra == 'all'
Requires-Dist: slackclient (>=1.0.0); extra == 'all'
Requires-Dist: cryptography (>=0.9.3); extra == 'all'
Requires-Dist: cx-Oracle (>=5.1.2); extra == 'all'
Requires-Dist: docker (>=2.0.0); extra == 'all'
Requires-Dist: paramiko (>=2.1.1); extra == 'all'
Requires-Dist: pysftp (>=0.2.9); extra == 'all'
Requires-Dist: kubernetes (>=3.0.0); extra == 'all'
Requires-Dist: cryptography (>=2.0.0); extra == 'all'
Requires-Dist: celery (<4.2.0,>=4.1.1); extra == 'all'
Requires-Dist: flower (<1.0,>=0.7.3); extra == 'all'
Requires-Dist: azure-storage (>=0.34.0); extra == 'all'
Requires-Dist: redis (>=2.10.5); extra == 'all'
Requires-Dist: httplib2 (>=0.9.2); extra == 'all'
Requires-Dist: google-api-python-client (<2.0.0dev,>=1.6.0); extra == 'all'
Requires-Dist: google-auth (<2.0.0dev,>=1.0.0); extra == 'all'
Requires-Dist: google-auth-httplib2 (>=0.0.1); extra == 'all'
Requires-Dist: google-cloud-container (>=0.1.1); extra == 'all'
Requires-Dist: PyOpenSSL; extra == 'all'
Requires-Dist: pandas-gbq; extra == 'all'
Requires-Dist: datadog (>=0.14.0); extra == 'all'
Requires-Dist: zdesk; extra == 'all'
Requires-Dist: jaydebeapi (>=1.1.1); extra == 'all'
Requires-Dist: ldap3 (>=0.9.9.1); extra == 'all'
Requires-Dist: pykerberos (>=1.1.13); extra == 'all'
Requires-Dist: requests-kerberos (>=0.10.0); extra == 'all'
Requires-Dist: thrift-sasl (>=0.2.0); extra == 'all'
Requires-Dist: snakebite[kerberos] (>=2.7.8); extra == 'all'
Requires-Dist: bcrypt (>=2.0.0); extra == 'all'
Requires-Dist: flask-bcrypt (>=0.7.1); extra == 'all'
Requires-Dist: hdfs[avro,dataframe,kerberos] (>=2.0.4); extra == 'all'
Requires-Dist: python-jenkins (>=0.4.15); extra == 'all'
Requires-Dist: pydruid (>=0.4.1); extra == 'all'
Requires-Dist: pinotdb (>=0.1.1); extra == 'all'
Requires-Dist: analytics-python (>=1.2.9); extra == 'all'
Requires-Dist: snowflake-connector-python (>=1.5.2); extra == 'all'
Requires-Dist: snowflake-sqlalchemy (>=1.1.0); extra == 'all'
Requires-Dist: elasticsearch (<6.0.0,>=5.0.0); extra == 'all'
Requires-Dist: elasticsearch-dsl (<6.0.0,>=5.0.0); extra == 'all'
Requires-Dist: azure-mgmt-resource (==1.2.2); extra == 'all'
Requires-Dist: azure-mgmt-datalake-store (==0.4.0); extra == 'all'
Requires-Dist: azure-datalake-store (==0.0.19); extra == 'all'
Requires-Dist: atlasclient (>=0.1.2); extra == 'all'
Provides-Extra: all_dbs
Requires-Dist: psycopg2-binary (>=2.7.4); extra == 'all_dbs'
Requires-Dist: mysqlclient (>=1.3.6); extra == 'all_dbs'
Requires-Dist: hmsclient (>=0.1.0); extra == 'all_dbs'
Requires-Dist: pyhive (>=0.6.0); extra == 'all_dbs'
Requires-Dist: pymssql (>=2.1.1); extra == 'all_dbs'
Requires-Dist: snakebite (>=2.7.8); extra == 'all_dbs'
Requires-Dist: vertica-python (>=0.5.1); extra == 'all_dbs'
Requires-Dist: cloudant (<2.0,>=0.5.9); extra == 'all_dbs'
Requires-Dist: pydruid (>=0.4.1); extra == 'all_dbs'
Requires-Dist: pinotdb (>=0.1.1); extra == 'all_dbs'
Requires-Dist: cassandra-driver (>=3.13.0); extra == 'all_dbs'
Requires-Dist: pymongo (>=3.6.0); extra == 'all_dbs'
Provides-Extra: async
Requires-Dist: greenlet (>=0.4.9); extra == 'async'
Requires-Dist: eventlet (>=0.9.7); extra == 'async'
Requires-Dist: gevent (>=0.13); extra == 'async'
Provides-Extra: atlas
Requires-Dist: atlasclient (>=0.1.2); extra == 'atlas'
Provides-Extra: azure_blob_storage
Requires-Dist: azure-storage (>=0.34.0); extra == 'azure_blob_storage'
Provides-Extra: azure_data_lake
Requires-Dist: azure-mgmt-resource (==1.2.2); extra == 'azure_data_lake'
Requires-Dist: azure-mgmt-datalake-store (==0.4.0); extra == 'azure_data_lake'
Requires-Dist: azure-datalake-store (==0.0.19); extra == 'azure_data_lake'
Provides-Extra: cassandra
Requires-Dist: cassandra-driver (>=3.13.0); extra == 'cassandra'
Provides-Extra: celery
Requires-Dist: celery (<4.2.0,>=4.1.1); extra == 'celery'
Requires-Dist: flower (<1.0,>=0.7.3); extra == 'celery'
Provides-Extra: cgroups
Requires-Dist: cgroupspy (>=0.1.4); extra == 'cgroups'
Provides-Extra: cloudant
Requires-Dist: cloudant (<2.0,>=0.5.9); extra == 'cloudant'
Provides-Extra: crypto
Requires-Dist: cryptography (>=0.9.3); extra == 'crypto'
Provides-Extra: dask
Requires-Dist: distributed (<2,>=1.17.1); extra == 'dask'
Provides-Extra: databricks
Requires-Dist: requests (<3,>=2.5.1); extra == 'databricks'
Provides-Extra: datadog
Requires-Dist: datadog (>=0.14.0); extra == 'datadog'
Provides-Extra: devel
Requires-Dist: click; extra == 'devel'
Requires-Dist: freezegun; extra == 'devel'
Requires-Dist: jira; extra == 'devel'
Requires-Dist: lxml (>=3.3.4); extra == 'devel'
Requires-Dist: mock; extra == 'devel'
Requires-Dist: mongomock; extra == 'devel'
Requires-Dist: moto (==1.1.19); extra == 'devel'
Requires-Dist: nose; extra == 'devel'
Requires-Dist: nose-ignore-docstring (==0.2); extra == 'devel'
Requires-Dist: nose-timer; extra == 'devel'
Requires-Dist: parameterized; extra == 'devel'
Requires-Dist: paramiko; extra == 'devel'
Requires-Dist: pysftp; extra == 'devel'
Requires-Dist: pywinrm; extra == 'devel'
Requires-Dist: qds-sdk (>=1.9.6); extra == 'devel'
Requires-Dist: rednose; extra == 'devel'
Requires-Dist: requests-mock; extra == 'devel'
Requires-Dist: kubernetes (>=3.0.0); extra == 'devel'
Requires-Dist: cryptography (>=2.0.0); extra == 'devel'
Requires-Dist: mysqlclient (>=1.3.6); extra == 'devel'
Requires-Dist: sphinx (>=1.2.3); extra == 'devel'
Requires-Dist: sphinx-argparse (>=0.1.13); extra == 'devel'
Requires-Dist: sphinx-rtd-theme (>=0.1.6); extra == 'devel'
Requires-Dist: Sphinx-PyPI-upload (>=0.2.1); extra == 'devel'
Requires-Dist: bcrypt (>=2.0.0); extra == 'devel'
Requires-Dist: flask-bcrypt (>=0.7.1); extra == 'devel'
Requires-Dist: boto3 (>=1.7.0); extra == 'devel'
Requires-Dist: cgroupspy (>=0.1.4); extra == 'devel'
Provides-Extra: devel_ci
Requires-Dist: sendgrid (>=5.2.0); extra == 'devel_ci'
Requires-Dist: click; extra == 'devel_ci'
Requires-Dist: freezegun; extra == 'devel_ci'
Requires-Dist: jira; extra == 'devel_ci'
Requires-Dist: lxml (>=3.3.4); extra == 'devel_ci'
Requires-Dist: mock; extra == 'devel_ci'
Requires-Dist: mongomock; extra == 'devel_ci'
Requires-Dist: moto (==1.1.19); extra == 'devel_ci'
Requires-Dist: nose; extra == 'devel_ci'
Requires-Dist: nose-ignore-docstring (==0.2); extra == 'devel_ci'
Requires-Dist: nose-timer; extra == 'devel_ci'
Requires-Dist: parameterized; extra == 'devel_ci'
Requires-Dist: paramiko; extra == 'devel_ci'
Requires-Dist: pysftp; extra == 'devel_ci'
Requires-Dist: pywinrm; extra == 'devel_ci'
Requires-Dist: qds-sdk (>=1.9.6); extra == 'devel_ci'
Requires-Dist: rednose; extra == 'devel_ci'
Requires-Dist: requests-mock; extra == 'devel_ci'
Requires-Dist: psycopg2-binary (>=2.7.4); extra == 'devel_ci'
Requires-Dist: mysqlclient (>=1.3.6); extra == 'devel_ci'
Requires-Dist: hmsclient (>=0.1.0); extra == 'devel_ci'
Requires-Dist: pyhive (>=0.6.0); extra == 'devel_ci'
Requires-Dist: pymssql (>=2.1.1); extra == 'devel_ci'
Requires-Dist: vertica-python (>=0.5.1); extra == 'devel_ci'
Requires-Dist: cloudant (<2.0,>=0.5.9); extra == 'devel_ci'
Requires-Dist: pydruid (>=0.4.1); extra == 'devel_ci'
Requires-Dist: pinotdb (>=0.1.1); extra == 'devel_ci'
Requires-Dist: cassandra-driver (>=3.13.0); extra == 'devel_ci'
Requires-Dist: pymongo (>=3.6.0); extra == 'devel_ci'
Requires-Dist: sphinx (>=1.2.3); extra == 'devel_ci'
Requires-Dist: sphinx-argparse (>=0.1.13); extra == 'devel_ci'
Requires-Dist: sphinx-rtd-theme (>=0.1.6); extra == 'devel_ci'
Requires-Dist: Sphinx-PyPI-upload (>=0.2.1); extra == 'devel_ci'
Requires-Dist: pysmbclient (>=0.1.3); extra == 'devel_ci'
Requires-Dist: boto3 (>=1.7.0); extra == 'devel_ci'
Requires-Dist: slackclient (>=1.0.0); extra == 'devel_ci'
Requires-Dist: cryptography (>=0.9.3); extra == 'devel_ci'
Requires-Dist: cx-Oracle (>=5.1.2); extra == 'devel_ci'
Requires-Dist: docker (>=2.0.0); extra == 'devel_ci'
Requires-Dist: paramiko (>=2.1.1); extra == 'devel_ci'
Requires-Dist: pysftp (>=0.2.9); extra == 'devel_ci'
Requires-Dist: kubernetes (>=3.0.0); extra == 'devel_ci'
Requires-Dist: cryptography (>=2.0.0); extra == 'devel_ci'
Requires-Dist: celery (<4.2.0,>=4.1.1); extra == 'devel_ci'
Requires-Dist: flower (<1.0,>=0.7.3); extra == 'devel_ci'
Requires-Dist: azure-storage (>=0.34.0); extra == 'devel_ci'
Requires-Dist: redis (>=2.10.5); extra == 'devel_ci'
Requires-Dist: httplib2 (>=0.9.2); extra == 'devel_ci'
Requires-Dist: google-api-python-client (<2.0.0dev,>=1.6.0); extra == 'devel_ci'
Requires-Dist: google-auth (<2.0.0dev,>=1.0.0); extra == 'devel_ci'
Requires-Dist: google-auth-httplib2 (>=0.0.1); extra == 'devel_ci'
Requires-Dist: google-cloud-container (>=0.1.1); extra == 'devel_ci'
Requires-Dist: PyOpenSSL; extra == 'devel_ci'
Requires-Dist: pandas-gbq; extra == 'devel_ci'
Requires-Dist: datadog (>=0.14.0); extra == 'devel_ci'
Requires-Dist: zdesk; extra == 'devel_ci'
Requires-Dist: jaydebeapi (>=1.1.1); extra == 'devel_ci'
Requires-Dist: ldap3 (>=0.9.9.1); extra == 'devel_ci'
Requires-Dist: pykerberos (>=1.1.13); extra == 'devel_ci'
Requires-Dist: requests-kerberos (>=0.10.0); extra == 'devel_ci'
Requires-Dist: thrift-sasl (>=0.2.0); extra == 'devel_ci'
Requires-Dist: bcrypt (>=2.0.0); extra == 'devel_ci'
Requires-Dist: flask-bcrypt (>=0.7.1); extra == 'devel_ci'
Requires-Dist: hdfs[avro,dataframe,kerberos] (>=2.0.4); extra == 'devel_ci'
Requires-Dist: python-jenkins (>=0.4.15); extra == 'devel_ci'
Requires-Dist: pydruid (>=0.4.1); extra == 'devel_ci'
Requires-Dist: pinotdb (>=0.1.1); extra == 'devel_ci'
Requires-Dist: analytics-python (>=1.2.9); extra == 'devel_ci'
Requires-Dist: snowflake-connector-python (>=1.5.2); extra == 'devel_ci'
Requires-Dist: snowflake-sqlalchemy (>=1.1.0); extra == 'devel_ci'
Requires-Dist: elasticsearch (<6.0.0,>=5.0.0); extra == 'devel_ci'
Requires-Dist: elasticsearch-dsl (<6.0.0,>=5.0.0); extra == 'devel_ci'
Requires-Dist: azure-mgmt-resource (==1.2.2); extra == 'devel_ci'
Requires-Dist: azure-mgmt-datalake-store (==0.4.0); extra == 'devel_ci'
Requires-Dist: azure-datalake-store (==0.0.19); extra == 'devel_ci'
Requires-Dist: atlasclient (>=0.1.2); extra == 'devel_ci'
Provides-Extra: devel_hadoop
Requires-Dist: click; extra == 'devel_hadoop'
Requires-Dist: freezegun; extra == 'devel_hadoop'
Requires-Dist: jira; extra == 'devel_hadoop'
Requires-Dist: lxml (>=3.3.4); extra == 'devel_hadoop'
Requires-Dist: mock; extra == 'devel_hadoop'
Requires-Dist: mongomock; extra == 'devel_hadoop'
Requires-Dist: moto (==1.1.19); extra == 'devel_hadoop'
Requires-Dist: nose; extra == 'devel_hadoop'
Requires-Dist: nose-ignore-docstring (==0.2); extra == 'devel_hadoop'
Requires-Dist: nose-timer; extra == 'devel_hadoop'
Requires-Dist: parameterized; extra == 'devel_hadoop'
Requires-Dist: paramiko; extra == 'devel_hadoop'
Requires-Dist: pysftp; extra == 'devel_hadoop'
Requires-Dist: pywinrm; extra == 'devel_hadoop'
Requires-Dist: qds-sdk (>=1.9.6); extra == 'devel_hadoop'
Requires-Dist: rednose; extra == 'devel_hadoop'
Requires-Dist: requests-mock; extra == 'devel_hadoop'
Requires-Dist: kubernetes (>=3.0.0); extra == 'devel_hadoop'
Requires-Dist: cryptography (>=2.0.0); extra == 'devel_hadoop'
Requires-Dist: mysqlclient (>=1.3.6); extra == 'devel_hadoop'
Requires-Dist: sphinx (>=1.2.3); extra == 'devel_hadoop'
Requires-Dist: sphinx-argparse (>=0.1.13); extra == 'devel_hadoop'
Requires-Dist: sphinx-rtd-theme (>=0.1.6); extra == 'devel_hadoop'
Requires-Dist: Sphinx-PyPI-upload (>=0.2.1); extra == 'devel_hadoop'
Requires-Dist: bcrypt (>=2.0.0); extra == 'devel_hadoop'
Requires-Dist: flask-bcrypt (>=0.7.1); extra == 'devel_hadoop'
Requires-Dist: boto3 (>=1.7.0); extra == 'devel_hadoop'
Requires-Dist: cgroupspy (>=0.1.4); extra == 'devel_hadoop'
Requires-Dist: hmsclient (>=0.1.0); extra == 'devel_hadoop'
Requires-Dist: pyhive (>=0.6.0); extra == 'devel_hadoop'
Requires-Dist: snakebite (>=2.7.8); extra == 'devel_hadoop'
Requires-Dist: hdfs[avro,dataframe,kerberos] (>=2.0.4); extra == 'devel_hadoop'
Requires-Dist: pykerberos (>=1.1.13); extra == 'devel_hadoop'
Requires-Dist: requests-kerberos (>=0.10.0); extra == 'devel_hadoop'
Requires-Dist: thrift-sasl (>=0.2.0); extra == 'devel_hadoop'
Requires-Dist: snakebite[kerberos] (>=2.7.8); extra == 'devel_hadoop'
Provides-Extra: doc
Requires-Dist: sphinx (>=1.2.3); extra == 'doc'
Requires-Dist: sphinx-argparse (>=0.1.13); extra == 'doc'
Requires-Dist: sphinx-rtd-theme (>=0.1.6); extra == 'doc'
Requires-Dist: Sphinx-PyPI-upload (>=0.2.1); extra == 'doc'
Provides-Extra: docker
Requires-Dist: docker (>=2.0.0); extra == 'docker'
Provides-Extra: druid
Requires-Dist: pydruid (>=0.4.1); extra == 'druid'
Provides-Extra: elasticsearch
Requires-Dist: elasticsearch (<6.0.0,>=5.0.0); extra == 'elasticsearch'
Requires-Dist: elasticsearch-dsl (<6.0.0,>=5.0.0); extra == 'elasticsearch'
Provides-Extra: emr
Requires-Dist: boto3 (>=1.0.0); extra == 'emr'
Provides-Extra: gcp_api
Requires-Dist: httplib2 (>=0.9.2); extra == 'gcp_api'
Requires-Dist: google-api-python-client (<2.0.0dev,>=1.6.0); extra == 'gcp_api'
Requires-Dist: google-auth (<2.0.0dev,>=1.0.0); extra == 'gcp_api'
Requires-Dist: google-auth-httplib2 (>=0.0.1); extra == 'gcp_api'
Requires-Dist: google-cloud-container (>=0.1.1); extra == 'gcp_api'
Requires-Dist: PyOpenSSL; extra == 'gcp_api'
Requires-Dist: pandas-gbq; extra == 'gcp_api'
Provides-Extra: github_enterprise
Requires-Dist: Flask-OAuthlib (>=0.9.1); extra == 'github_enterprise'
Provides-Extra: hdfs
Requires-Dist: snakebite (>=2.7.8); extra == 'hdfs'
Provides-Extra: hive
Requires-Dist: hmsclient (>=0.1.0); extra == 'hive'
Requires-Dist: pyhive (>=0.6.0); extra == 'hive'
Provides-Extra: jdbc
Requires-Dist: jaydebeapi (>=1.1.1); extra == 'jdbc'
Provides-Extra: jira
Requires-Dist: JIRA (>1.0.7); extra == 'jira'
Provides-Extra: kerberos
Requires-Dist: pykerberos (>=1.1.13); extra == 'kerberos'
Requires-Dist: requests-kerberos (>=0.10.0); extra == 'kerberos'
Requires-Dist: thrift-sasl (>=0.2.0); extra == 'kerberos'
Requires-Dist: snakebite[kerberos] (>=2.7.8); extra == 'kerberos'
Provides-Extra: kubernetes
Requires-Dist: kubernetes (>=3.0.0); extra == 'kubernetes'
Requires-Dist: cryptography (>=2.0.0); extra == 'kubernetes'
Provides-Extra: ldap
Requires-Dist: ldap3 (>=0.9.9.1); extra == 'ldap'
Provides-Extra: mongo
Requires-Dist: pymongo (>=3.6.0); extra == 'mongo'
Provides-Extra: mssql
Requires-Dist: pymssql (>=2.1.1); extra == 'mssql'
Provides-Extra: mysql
Requires-Dist: mysqlclient (>=1.3.6); extra == 'mysql'
Provides-Extra: oracle
Requires-Dist: cx-Oracle (>=5.1.2); extra == 'oracle'
Provides-Extra: password
Requires-Dist: bcrypt (>=2.0.0); extra == 'password'
Requires-Dist: flask-bcrypt (>=0.7.1); extra == 'password'
Provides-Extra: pinot
Requires-Dist: pinotdb (>=0.1.1); extra == 'pinot'
Provides-Extra: postgres
Requires-Dist: psycopg2-binary (>=2.7.4); extra == 'postgres'
Provides-Extra: qds
Requires-Dist: qds-sdk (>=1.9.6); extra == 'qds'
Provides-Extra: rabbitmq
Requires-Dist: librabbitmq (>=1.6.1); extra == 'rabbitmq'
Provides-Extra: redis
Requires-Dist: redis (>=2.10.5); extra == 'redis'
Provides-Extra: s3
Requires-Dist: boto3 (>=1.7.0); extra == 's3'
Provides-Extra: salesforce
Requires-Dist: simple-salesforce (>=0.72); extra == 'salesforce'
Provides-Extra: samba
Requires-Dist: pysmbclient (>=0.1.3); extra == 'samba'
Provides-Extra: segment
Requires-Dist: analytics-python (>=1.2.9); extra == 'segment'
Provides-Extra: sendgrid
Requires-Dist: sendgrid (>=5.2.0); extra == 'sendgrid'
Provides-Extra: slack
Requires-Dist: slackclient (>=1.0.0); extra == 'slack'
Provides-Extra: snowflake
Requires-Dist: snowflake-connector-python (>=1.5.2); extra == 'snowflake'
Requires-Dist: snowflake-sqlalchemy (>=1.1.0); extra == 'snowflake'
Provides-Extra: ssh
Requires-Dist: paramiko (>=2.1.1); extra == 'ssh'
Requires-Dist: pysftp (>=0.2.9); extra == 'ssh'
Provides-Extra: statsd
Requires-Dist: statsd (<4.0,>=3.0.1); extra == 'statsd'
Provides-Extra: vertica
Requires-Dist: vertica-python (>=0.5.1); extra == 'vertica'
Provides-Extra: webhdfs
Requires-Dist: hdfs[avro,dataframe,kerberos] (>=2.0.4); extra == 'webhdfs'
Provides-Extra: winrm
Requires-Dist: pywinrm (==0.2.2); extra == 'winrm'
